channels_auth_token_middlewares/__init__.py
channels_auth_token_middlewares/apps.py
channels_auth_token_middlewares/middleware/__init__.py
channels_auth_token_middlewares/middleware/base.py
channels_auth_token_middlewares/middleware/drf.py
channels_auth_token_middlewares-1.3.1.dist-info/METADATA
channels_auth_token_middlewares-1.3.1.dist-info/WHEEL
channels_auth_token_middlewares-1.3.1.dist-info/licenses/LICENSE
channels_auth_token_middlewares-1.3.1.dist-info/RECORD
