Metadata-Version: 2.4
Name: channels_auth_token_middlewares
Version: 1.3.1
Summary: Django Channels auth token middlewares
Project-URL: Homepage, https://github.com/YegorDB/django-channels-auth-token-middlewares
Author-email: Yegor Bitensky <yegorbitensky@gmail.com>
License-Expression: Apache-2.0
License-File: LICENSE
Keywords: channels,django,middleware
Classifier: Development Status :: 5 - Production/Stable
Classifier: Intended Audience :: Developers
Classifier: Programming Language :: Python
Classifier: Programming Language :: Python :: 3
Classifier: Programming Language :: Python :: 3 :: Only
Classifier: Programming Language :: Python :: 3.8
Classifier: Programming Language :: Python :: 3.9
Classifier: Programming Language :: Python :: 3.10
Classifier: Programming Language :: Python :: 3.11
Classifier: Programming Language :: Python :: 3.12
Classifier: Programming Language :: Python :: 3.13
Classifier: Programming Language :: Python :: 3.14
Classifier: Topic :: Software Development
Requires-Python: >=3.8
Requires-Dist: channels>=4.1.0
